freesound.py
freesound_api-1.1.0.2.dist-info/COPYING.txt
freesound_api-1.1.0.2.dist-info/WHEEL
freesound_api-1.1.0.2.dist-info/METADATA
freesound_api-1.1.0.2.dist-info/RECORD
