Metadata-Version: 2.1
Name: freesound-api
Version: 1.1.0.2
Summary: A Python client for the Freesound APIv2. Clone of freesound-python.
Home-page: https://github.com/ilesinge/freesound-api
License: MIT
Author: Universitat Pompeu Fabra
Maintainer: Alexandre Gravel-Raymond
Maintainer-email: alex@ndre.gr
Requires-Python: >=3.6,<4.0
Classifier: License :: OSI Approved :: MIT License
Classifier: Programming Language :: Python :: 3
Classifier: Programming Language :: Python :: 3.6
Classifier: Programming Language :: Python :: 3.7
Classifier: Programming Language :: Python :: 3.8
Classifier: Programming Language :: Python :: 3.9
Classifier: Programming Language :: Python :: 3.10
Classifier: Programming Language :: Python :: 3.11
Requires-Dist: requests (>2.27,<3.0)
Project-URL: Repository, https://github.com/ilesinge/freesound-api
